TeleClient/__init__.py
TeleClient/client.py
TeleClient/env.py
TeleClient/errors.py
telethon_client-0.1.9.dist-info/METADATA
telethon_client-0.1.9.dist-info/WHEEL
telethon_client-0.1.9.dist-info/top_level.txt
telethon_client-0.1.9.dist-info/RECORD
