Metadata-Version: 2.1
Name: telethon-client
Version: 0.1.9
Summary: Custom Telethon Client for My Usage
Author: LEGENDX
Author-email: legendxcoder@gmail.com
Classifier: Programming Language :: Python :: 3
Classifier: License :: OSI Approved :: MIT License
Classifier: Operating System :: OS Independent
Requires-Python: >=3.7
Requires-Dist: Telethon >=1.35.0
Requires-Dist: requests >=2.32.3
